README.rst
setup.py
authentication/__init__.py
authentication/admin.py
authentication/apps.py
authentication/middlewares.py
authentication/models.py
authentication/permissions.py
authentication/serializers.py
authentication/services.py
authentication/tests.py
authentication/urls.py
authentication/views.py
vtc_djangoauth.egg-info/PKG-INFO
vtc_djangoauth.egg-info/SOURCES.txt
vtc_djangoauth.egg-info/dependency_links.txt
vtc_djangoauth.egg-info/requires.txt
vtc_djangoauth.egg-info/top_level.txt